wrapperz/__init__.py
wrapperz/py.typed
wrapperz/api/__init__.py
wrapperz/api/asr.py
wrapperz/api/llm.py
wrapperz/api/messages.py
wrapperz/api/tts.py
wrapperz-0.1.3.dist-info/METADATA
wrapperz-0.1.3.dist-info/WHEEL
wrapperz-0.1.3.dist-info/RECORD
